_acb_speedup.cpython-310-darwin.so
acb/__init__.py
acb/__main__.py
acb/acb.py
acb/disarm.py
acb/py.typed
acb/utf.py
acb_py-1.2.4.dist-info/LICENSE
acb_py-1.2.4.dist-info/METADATA
acb_py-1.2.4.dist-info/WHEEL
acb_py-1.2.4.dist-info/entry_points.txt
acb_py-1.2.4.dist-info/top_level.txt
acb_py-1.2.4.dist-info/RECORD
