Metadata-Version: 2.1
Name: acb-py
Version: 1.2.4
Summary: Library for reading/extracting ACB files
Home-page: https://github.com/summertriangle-dev/acb.py
Author: The Holy Constituency of the Summer Triangle
Author-email: summertriangle.dev@gmail.com
Classifier: Programming Language :: Python :: 3
Classifier: License :: OSI Approved :: MIT License
Classifier: Operating System :: OS Independent
Classifier: Topic :: System :: Archiving
Requires-Python: >=3.6
License-File: LICENSE
